[
    {
        "sensor_id": "400001",
        "position": [
            37.364085,
            -121.901149
        ],
        "content": "400001 : 37.364085 , -121.901149"
    },
    {
        "sensor_id": "400017",
        "position": [
            37.253303,
            -121.94544
        ],
        "content": "400017 : 37.253303 , -121.94544"
    },
    {
        "sensor_id": "400030",
        "position": [
            37.359087,
            -121.906538
        ],
        "content": "400030 : 37.359087 , -121.906538"
    },
    {
        "sensor_id": "400040",
        "position": [
            37.294949,
            -121.873109
        ],
        "content": "400040 : 37.294949 , -121.873109"
    },
    {
        "sensor_id": "400045",
        "position": [
            37.363402,
            -121.902233
        ],
        "content": "400045 : 37.363402 , -121.902233"
    },
    {
        "sensor_id": "400052",
        "position": [
            37.255791,
            -121.875479
        ],
        "content": "400052 : 37.255791 , -121.875479"
    },
    {
        "sensor_id": "400057",
        "position": [
            37.335022,
            -121.935522
        ],
        "content": "400057 : 37.335022 , -121.935522"
    },
    {
        "sensor_id": "400059",
        "position": [
            37.250481,
            -121.907735
        ],
        "content": "400059 : 37.250481 , -121.907735"
    },
    {
        "sensor_id": "400065",
        "position": [
            37.320292,
            -121.890281
        ],
        "content": "400065 : 37.320292 , -121.890281"
    },
    {
        "sensor_id": "400069",
        "position": [
            37.385758,
            -121.977493
        ],
        "content": "400069 : 37.385758 , -121.977493"
    },
    {
        "sensor_id": "400073",
        "position": [
            37.2563,
            -121.955559
        ],
        "content": "400073 : 37.2563 , -121.955559"
    },
    {
        "sensor_id": "400084",
        "position": [
            37.329258,
            -122.012053
        ],
        "content": "400084 : 37.329258 , -122.012053"
    },
    {
        "sensor_id": "400085",
        "position": [
            37.255594,
            -121.87471
        ],
        "content": "400085 : 37.255594 , -121.87471"
    },
    {
        "sensor_id": "400088",
        "position": [
            37.414988,
            -121.912685
        ],
        "content": "400088 : 37.414988 , -121.912685"
    },
    {
        "sensor_id": "400096",
        "position": [
            37.417981,
            -121.972547
        ],
        "content": "400096 : 37.417981 , -121.972547"
    },
    {
        "sensor_id": "400097",
        "position": [
            37.279012,
            -122.010614
        ],
        "content": "400097 : 37.279012 , -122.010614"
    },
    {
        "sensor_id": "400100",
        "position": [
            37.295052,
            -121.938872
        ],
        "content": "400100 : 37.295052 , -121.938872"
    },
    {
        "sensor_id": "400104",
        "position": [
            37.419313,
            -121.95548
        ],
        "content": "400104 : 37.419313 , -121.95548"
    },
    {
        "sensor_id": "400109",
        "position": [
            37.362706,
            -121.889426
        ],
        "content": "400109 : 37.362706 , -121.889426"
    },
    {
        "sensor_id": "400122",
        "position": [
            37.36614,
            -121.901132
        ],
        "content": "400122 : 37.36614 , -121.901132"
    },
    {
        "sensor_id": "400147",
        "position": [
            37.34221,
            -121.926305
        ],
        "content": "400147 : 37.34221 , -121.926305"
    },
    {
        "sensor_id": "400148",
        "position": [
            37.250664,
            -121.912479
        ],
        "content": "400148 : 37.250664 , -121.912479"
    },
    {
        "sensor_id": "400149",
        "position": [
            37.4118,
            -122.077964
        ],
        "content": "400149 : 37.4118 , -122.077964"
    },
    {
        "sensor_id": "400158",
        "position": [
            37.421059,
            -121.93678
        ],
        "content": "400158 : 37.421059 , -121.93678"
    },
    {
        "sensor_id": "400160",
        "position": [
            37.348392,
            -121.860589
        ],
        "content": "400160 : 37.348392 , -121.860589"
    },
    {
        "sensor_id": "400168",
        "position": [
            37.391166,
            -121.995524
        ],
        "content": "400168 : 37.391166 , -121.995524"
    },
    {
        "sensor_id": "400172",
        "position": [
            37.376264,
            -121.939712
        ],
        "content": "400172 : 37.376264 , -121.939712"
    },
    {
        "sensor_id": "400174",
        "position": [
            37.403686,
            -122.06976
        ],
        "content": "400174 : 37.403686 , -122.06976"
    },
    {
        "sensor_id": "400178",
        "position": [
            37.276874,
            -121.863698
        ],
        "content": "400178 : 37.276874 , -121.863698"
    },
    {
        "sensor_id": "400185",
        "position": [
            37.303131,
            -122.034527
        ],
        "content": "400185 : 37.303131 , -122.034527"
    },
    {
        "sensor_id": "400201",
        "position": [
            37.419186,
            -121.962831
        ],
        "content": "400201 : 37.419186 , -121.962831"
    },
    {
        "sensor_id": "400206",
        "position": [
            37.381356,
            -121.96211
        ],
        "content": "400206 : 37.381356 , -121.96211"
    },
    {
        "sensor_id": "400209",
        "position": [
            37.319961,
            -122.049031
        ],
        "content": "400209 : 37.319961 , -122.049031"
    },
    {
        "sensor_id": "400213",
        "position": [
            37.259192,
            -121.967128
        ],
        "content": "400213 : 37.259192 , -121.967128"
    },
    {
        "sensor_id": "400221",
        "position": [
            37.293614,
            -121.937899
        ],
        "content": "400221 : 37.293614 , -121.937899"
    },
    {
        "sensor_id": "400222",
        "position": [
            37.275395,
            -122.004702
        ],
        "content": "400222 : 37.275395 , -122.004702"
    },
    {
        "sensor_id": "400227",
        "position": [
            37.377237,
            -121.943586
        ],
        "content": "400227 : 37.377237 , -121.943586"
    },
    {
        "sensor_id": "400236",
        "position": [
            37.325009,
            -121.892984
        ],
        "content": "400236 : 37.325009 , -121.892984"
    },
    {
        "sensor_id": "400238",
        "position": [
            37.413256,
            -121.912324
        ],
        "content": "400238 : 37.413256 , -121.912324"
    },
    {
        "sensor_id": "400240",
        "position": [
            37.258184,
            -121.953853
        ],
        "content": "400240 : 37.258184 , -121.953853"
    },
    {
        "sensor_id": "400246",
        "position": [
            37.386551,
            -121.979462
        ],
        "content": "400246 : 37.386551 , -121.979462"
    },
    {
        "sensor_id": "400253",
        "position": [
            37.342957,
            -121.925721
        ],
        "content": "400253 : 37.342957 , -121.925721"
    },
    {
        "sensor_id": "400257",
        "position": [
            37.291715,
            -121.871799
        ],
        "content": "400257 : 37.291715 , -121.871799"
    },
    {
        "sensor_id": "400258",
        "position": [
            37.313462,
            -121.886197
        ],
        "content": "400258 : 37.313462 , -121.886197"
    },
    {
        "sensor_id": "400268",
        "position": [
            37.255651,
            -121.858078
        ],
        "content": "400268 : 37.255651 , -121.858078"
    },
    {
        "sensor_id": "400274",
        "position": [
            37.409627,
            -121.997252
        ],
        "content": "400274 : 37.409627 , -121.997252"
    },
    {
        "sensor_id": "400278",
        "position": [
            37.266561,
            -121.948692
        ],
        "content": "400278 : 37.266561 , -121.948692"
    },
    {
        "sensor_id": "400280",
        "position": [
            37.26198,
            -121.858479
        ],
        "content": "400280 : 37.26198 , -121.858479"
    },
    {
        "sensor_id": "400292",
        "position": [
            37.316378,
            -121.972052
        ],
        "content": "400292 : 37.316378 , -121.972052"
    },
    {
        "sensor_id": "400296",
        "position": [
            37.420359,
            -121.93915
        ],
        "content": "400296 : 37.420359 , -121.93915"
    },
    {
        "sensor_id": "400298",
        "position": [
            37.293047,
            -121.937861
        ],
        "content": "400298 : 37.293047 , -121.937861"
    },
    {
        "sensor_id": "400330",
        "position": [
            37.398628,
            -122.026802
        ],
        "content": "400330 : 37.398628 , -122.026802"
    },
    {
        "sensor_id": "400336",
        "position": [
            37.250624,
            -121.928209
        ],
        "content": "400336 : 37.250624 , -121.928209"
    },
    {
        "sensor_id": "400343",
        "position": [
            37.348907,
            -121.917833
        ],
        "content": "400343 : 37.348907 , -121.917833"
    },
    {
        "sensor_id": "400353",
        "position": [
            37.383125,
            -121.967496
        ],
        "content": "400353 : 37.383125 , -121.967496"
    },
    {
        "sensor_id": "400372",
        "position": [
            37.38482,
            -121.974251
        ],
        "content": "400372 : 37.38482 , -121.974251"
    },
    {
        "sensor_id": "400394",
        "position": [
            37.364382,
            -121.902692
        ],
        "content": "400394 : 37.364382 , -121.902692"
    },
    {
        "sensor_id": "400400",
        "position": [
            37.34241,
            -121.854543
        ],
        "content": "400400 : 37.34241 , -121.854543"
    },
    {
        "sensor_id": "400414",
        "position": [
            37.317942,
            -121.977301
        ],
        "content": "400414 : 37.317942 , -121.977301"
    },
    {
        "sensor_id": "400418",
        "position": [
            37.291828,
            -121.871836
        ],
        "content": "400418 : 37.291828 , -121.871836"
    },
    {
        "sensor_id": "400429",
        "position": [
            37.319424,
            -121.993175
        ],
        "content": "400429 : 37.319424 , -121.993175"
    },
    {
        "sensor_id": "400435",
        "position": [
            37.403153,
            -122.047463
        ],
        "content": "400435 : 37.403153 , -122.047463"
    },
    {
        "sensor_id": "400436",
        "position": [
            37.271687,
            -121.947037
        ],
        "content": "400436 : 37.271687 , -121.947037"
    },
    {
        "sensor_id": "400440",
        "position": [
            37.353727,
            -121.865827
        ],
        "content": "400440 : 37.353727 , -121.865827"
    },
    {
        "sensor_id": "400449",
        "position": [
            37.419452,
            -121.955498
        ],
        "content": "400449 : 37.419452 , -121.955498"
    },
    {
        "sensor_id": "400457",
        "position": [
            37.276763,
            -121.863661
        ],
        "content": "400457 : 37.276763 , -121.863661"
    },
    {
        "sensor_id": "400461",
        "position": [
            37.254781,
            -121.878917
        ],
        "content": "400461 : 37.254781 , -121.878917"
    },
    {
        "sensor_id": "400464",
        "position": [
            37.258029,
            -121.962211
        ],
        "content": "400464 : 37.258029 , -121.962211"
    },
    {
        "sensor_id": "400479",
        "position": [
            37.362439,
            -121.903211
        ],
        "content": "400479 : 37.362439 , -121.903211"
    },
    {
        "sensor_id": "400485",
        "position": [
            37.254231,
            -121.949216
        ],
        "content": "400485 : 37.254231 , -121.949216"
    },
    {
        "sensor_id": "400499",
        "position": [
            37.331068,
            -122.014931
        ],
        "content": "400499 : 37.331068 , -122.014931"
    },
    {
        "sensor_id": "400507",
        "position": [
            37.298931,
            -122.029806
        ],
        "content": "400507 : 37.298931 , -122.029806"
    },
    {
        "sensor_id": "400508",
        "position": [
            37.34766,
            -121.919969
        ],
        "content": "400508 : 37.34766 , -121.919969"
    },
    {
        "sensor_id": "400514",
        "position": [
            37.334602,
            -121.936288
        ],
        "content": "400514 : 37.334602 , -121.936288"
    },
    {
        "sensor_id": "400519",
        "position": [
            37.255257,
            -121.85256
        ],
        "content": "400519 : 37.255257 , -121.85256"
    },
    {
        "sensor_id": "400528",
        "position": [
            37.388893,
            -122.068829
        ],
        "content": "400528 : 37.388893 , -122.068829"
    },
    {
        "sensor_id": "400545",
        "position": [
            37.40013,
            -122.033628
        ],
        "content": "400545 : 37.40013 , -122.033628"
    },
    {
        "sensor_id": "400560",
        "position": [
            37.324839,
            -122.002891
        ],
        "content": "400560 : 37.324839 , -122.002891"
    },
    {
        "sensor_id": "400563",
        "position": [
            37.325124,
            -121.893062
        ],
        "content": "400563 : 37.325124 , -121.893062"
    },
    {
        "sensor_id": "400567",
        "position": [
            37.418931,
            -121.962821
        ],
        "content": "400567 : 37.418931 , -121.962821"
    },
    {
        "sensor_id": "400581",
        "position": [
            37.402668,
            -122.029069
        ],
        "content": "400581 : 37.402668 , -122.029069"
    },
    {
        "sensor_id": "400582",
        "position": [
            37.275212,
            -122.004898
        ],
        "content": "400582 : 37.275212 , -122.004898"
    },
    {
        "sensor_id": "400586",
        "position": [
            37.376835,
            -121.942537
        ],
        "content": "400586 : 37.376835 , -121.942537"
    },
    {
        "sensor_id": "400637",
        "position": [
            37.255322,
            -121.855765
        ],
        "content": "400637 : 37.255322 , -121.855765"
    },
    {
        "sensor_id": "400643",
        "position": [
            37.390763,
            -121.994912
        ],
        "content": "400643 : 37.390763 , -121.994912"
    },
    {
        "sensor_id": "400648",
        "position": [
            37.303016,
            -122.034801
        ],
        "content": "400648 : 37.303016 , -122.034801"
    },
    {
        "sensor_id": "400649",
        "position": [
            37.251741,
            -121.958118
        ],
        "content": "400649 : 37.251741 , -121.958118"
    },
    {
        "sensor_id": "400654",
        "position": [
            37.297486,
            -121.874117
        ],
        "content": "400654 : 37.297486 , -121.874117"
    },
    {
        "sensor_id": "400664",
        "position": [
            37.303458,
            -121.878143
        ],
        "content": "400664 : 37.303458 , -121.878143"
    },
    {
        "sensor_id": "400665",
        "position": [
            37.341439,
            -121.849299
        ],
        "content": "400665 : 37.341439 , -121.849299"
    },
    {
        "sensor_id": "400668",
        "position": [
            37.35512,
            -121.866967
        ],
        "content": "400668 : 37.35512 , -121.866967"
    },
    {
        "sensor_id": "400673",
        "position": [
            37.329972,
            -122.013423
        ],
        "content": "400673 : 37.329972 , -122.013423"
    },
    {
        "sensor_id": "400677",
        "position": [
            37.32001,
            -122.048757
        ],
        "content": "400677 : 37.32001 , -122.048757"
    },
    {
        "sensor_id": "400687",
        "position": [
            37.408833,
            -122.000989
        ],
        "content": "400687 : 37.408833 , -122.000989"
    },
    {
        "sensor_id": "400688",
        "position": [
            37.259412,
            -121.966974
        ],
        "content": "400688 : 37.259412 , -121.966974"
    },
    {
        "sensor_id": "400690",
        "position": [
            37.255184,
            -121.876817
        ],
        "content": "400690 : 37.255184 , -121.876817"
    },
    {
        "sensor_id": "400700",
        "position": [
            37.251345,
            -121.934089
        ],
        "content": "400700 : 37.251345 , -121.934089"
    },
    {
        "sensor_id": "400709",
        "position": [
            37.341275,
            -121.927699
        ],
        "content": "400709 : 37.341275 , -121.927699"
    },
    {
        "sensor_id": "400713",
        "position": [
            37.251585,
            -121.934046
        ],
        "content": "400713 : 37.251585 , -121.934046"
    },
    {
        "sensor_id": "400714",
        "position": [
            37.316788,
            -121.953512
        ],
        "content": "400714 : 37.316788 , -121.953512"
    },
    {
        "sensor_id": "400715",
        "position": [
            37.256205,
            -121.955355
        ],
        "content": "400715 : 37.256205 , -121.955355"
    },
    {
        "sensor_id": "400717",
        "position": [
            37.250424,
            -121.912467
        ],
        "content": "400717 : 37.250424 , -121.912467"
    },
    {
        "sensor_id": "400723",
        "position": [
            37.334296,
            -121.936706
        ],
        "content": "400723 : 37.334296 , -121.936706"
    },
    {
        "sensor_id": "400743",
        "position": [
            37.398989,
            -122.028373
        ],
        "content": "400743 : 37.398989 , -122.028373"
    },
    {
        "sensor_id": "400750",
        "position": [
            37.250746,
            -121.907763
        ],
        "content": "400750 : 37.250746 , -121.907763"
    },
    {
        "sensor_id": "400760",
        "position": [
            37.374628,
            -121.931055
        ],
        "content": "400760 : 37.374628 , -121.931055"
    },
    {
        "sensor_id": "400772",
        "position": [
            37.250448,
            -121.928226
        ],
        "content": "400772 : 37.250448 , -121.928226"
    },
    {
        "sensor_id": "400790",
        "position": [
            37.391922,
            -121.998077
        ],
        "content": "400790 : 37.391922 , -121.998077"
    },
    {
        "sensor_id": "400792",
        "position": [
            37.255491,
            -121.955543
        ],
        "content": "400792 : 37.255491 , -121.955543"
    },
    {
        "sensor_id": "400794",
        "position": [
            37.390422,
            -121.993716
        ],
        "content": "400794 : 37.390422 , -121.993716"
    },
    {
        "sensor_id": "400799",
        "position": [
            37.327927,
            -121.876137
        ],
        "content": "400799 : 37.327927 , -121.876137"
    },
    {
        "sensor_id": "400804",
        "position": [
            37.336089,
            -121.848437
        ],
        "content": "400804 : 37.336089 , -121.848437"
    },
    {
        "sensor_id": "400822",
        "position": [
            37.255715,
            -121.955375
        ],
        "content": "400822 : 37.255715 , -121.955375"
    },
    {
        "sensor_id": "400823",
        "position": [
            37.334249,
            -122.030111
        ],
        "content": "400823 : 37.334249 , -122.030111"
    },
    {
        "sensor_id": "400828",
        "position": [
            37.298804,
            -122.030071
        ],
        "content": "400828 : 37.298804 , -122.030071"
    },
    {
        "sensor_id": "400832",
        "position": [
            37.254601,
            -121.956775
        ],
        "content": "400832 : 37.254601 , -121.956775"
    },
    {
        "sensor_id": "400837",
        "position": [
            37.303359,
            -121.878066
        ],
        "content": "400837 : 37.303359 , -121.878066"
    },
    {
        "sensor_id": "400842",
        "position": [
            37.261849,
            -121.859205
        ],
        "content": "400842 : 37.261849 , -121.859205"
    },
    {
        "sensor_id": "400863",
        "position": [
            37.371809,
            -121.91655
        ],
        "content": "400863 : 37.371809 , -121.91655"
    },
    {
        "sensor_id": "400869",
        "position": [
            37.403673,
            -122.069953
        ],
        "content": "400869 : 37.403673 , -122.069953"
    },
    {
        "sensor_id": "400873",
        "position": [
            37.420927,
            -121.93674
        ],
        "content": "400873 : 37.420927 , -121.93674"
    },
    {
        "sensor_id": "400895",
        "position": [
            37.380958,
            -121.960741
        ],
        "content": "400895 : 37.380958 , -121.960741"
    },
    {
        "sensor_id": "400904",
        "position": [
            37.395067,
            -122.010518
        ],
        "content": "400904 : 37.395067 , -122.010518"
    },
    {
        "sensor_id": "400907",
        "position": [
            37.257815,
            -121.96237
        ],
        "content": "400907 : 37.257815 , -121.96237"
    },
    {
        "sensor_id": "400911",
        "position": [
            37.372674,
            -121.922087
        ],
        "content": "400911 : 37.372674 , -121.922087"
    },
    {
        "sensor_id": "400916",
        "position": [
            37.320404,
            -121.89031
        ],
        "content": "400916 : 37.320404 , -121.89031"
    },
    {
        "sensor_id": "400922",
        "position": [
            37.363644,
            -121.899535
        ],
        "content": "400922 : 37.363644 , -121.899535"
    },
    {
        "sensor_id": "400934",
        "position": [
            37.254002,
            -121.949365
        ],
        "content": "400934 : 37.254002 , -121.949365"
    },
    {
        "sensor_id": "400951",
        "position": [
            37.325151,
            -121.940679
        ],
        "content": "400951 : 37.325151 , -121.940679"
    },
    {
        "sensor_id": "400952",
        "position": [
            37.279234,
            -122.01035
        ],
        "content": "400952 : 37.279234 , -122.01035"
    },
    {
        "sensor_id": "400953",
        "position": [
            37.327241,
            -121.88076
        ],
        "content": "400953 : 37.327241 , -121.88076"
    },
    {
        "sensor_id": "400964",
        "position": [
            37.376685,
            -121.94075
        ],
        "content": "400964 : 37.376685 , -121.94075"
    },
    {
        "sensor_id": "400965",
        "position": [
            37.363311,
            -121.893592
        ],
        "content": "400965 : 37.363311 , -121.893592"
    },
    {
        "sensor_id": "400970",
        "position": [
            37.409675,
            -121.996301
        ],
        "content": "400970 : 37.409675 , -121.996301"
    },
    {
        "sensor_id": "400971",
        "position": [
            37.368669,
            -121.901336
        ],
        "content": "400971 : 37.368669 , -121.901336"
    },
    {
        "sensor_id": "400973",
        "position": [
            37.417735,
            -121.972451
        ],
        "content": "400973 : 37.417735 , -121.972451"
    },
    {
        "sensor_id": "400995",
        "position": [
            37.313375,
            -121.886106
        ],
        "content": "400995 : 37.313375 , -121.886106"
    },
    {
        "sensor_id": "400996",
        "position": [
            37.350928,
            -121.862378
        ],
        "content": "400996 : 37.350928 , -121.862378"
    },
    {
        "sensor_id": "401014",
        "position": [
            37.420505,
            -121.9392
        ],
        "content": "401014 : 37.420505 , -121.9392"
    },
    {
        "sensor_id": "401129",
        "position": [
            37.266722,
            -121.859225
        ],
        "content": "401129 : 37.266722 , -121.859225"
    },
    {
        "sensor_id": "401154",
        "position": [
            37.266658,
            -121.85921
        ],
        "content": "401154 : 37.266658 , -121.85921"
    },
    {
        "sensor_id": "401163",
        "position": [
            37.316756,
            -121.923186
        ],
        "content": "401163 : 37.316756 , -121.923186"
    },
    {
        "sensor_id": "401167",
        "position": [
            37.316984,
            -121.923208
        ],
        "content": "401167 : 37.316984 , -121.923208"
    },
    {
        "sensor_id": "401210",
        "position": [
            37.291198,
            -122.023391
        ],
        "content": "401210 : 37.291198 , -122.023391"
    },
    {
        "sensor_id": "401224",
        "position": [
            37.291054,
            -122.023638
        ],
        "content": "401224 : 37.291054 , -122.023638"
    },
    {
        "sensor_id": "401327",
        "position": [
            37.315095,
            -121.914498
        ],
        "content": "401327 : 37.315095 , -121.914498"
    },
    {
        "sensor_id": "401351",
        "position": [
            37.401701,
            -122.032879
        ],
        "content": "401351 : 37.401701 , -122.032879"
    },
    {
        "sensor_id": "401388",
        "position": [
            37.316628,
            -121.952438
        ],
        "content": "401388 : 37.316628 , -121.952438"
    },
    {
        "sensor_id": "401391",
        "position": [
            37.337881,
            -121.85467
        ],
        "content": "401391 : 37.337881 , -121.85467"
    },
    {
        "sensor_id": "401400",
        "position": [
            37.316841,
            -121.952427
        ],
        "content": "401400 : 37.316841 , -121.952427"
    },
    {
        "sensor_id": "401403",
        "position": [
            37.338232,
            -121.854583
        ],
        "content": "401403 : 37.338232 , -121.854583"
    },
    {
        "sensor_id": "401440",
        "position": [
            37.356826,
            -121.908804
        ],
        "content": "401440 : 37.356826 , -121.908804"
    },
    {
        "sensor_id": "401457",
        "position": [
            37.279515,
            -121.864784
        ],
        "content": "401457 : 37.279515 , -121.864784"
    },
    {
        "sensor_id": "401464",
        "position": [
            37.424833,
            -121.916049
        ],
        "content": "401464 : 37.424833 , -121.916049"
    },
    {
        "sensor_id": "401489",
        "position": [
            37.427486,
            -121.916962
        ],
        "content": "401489 : 37.427486 , -121.916962"
    },
    {
        "sensor_id": "401495",
        "position": [
            37.255346,
            -121.85898
        ],
        "content": "401495 : 37.255346 , -121.85898"
    },
    {
        "sensor_id": "401507",
        "position": [
            37.412677,
            -122.079539
        ],
        "content": "401507 : 37.412677 , -122.079539"
    },
    {
        "sensor_id": "401534",
        "position": [
            37.407511,
            -122.065278
        ],
        "content": "401534 : 37.407511 , -122.065278"
    },
    {
        "sensor_id": "401541",
        "position": [
            37.370203,
            -121.901514
        ],
        "content": "401541 : 37.370203 , -121.901514"
    },
    {
        "sensor_id": "401555",
        "position": [
            37.255657,
            -121.858984
        ],
        "content": "401555 : 37.255657 , -121.858984"
    },
    {
        "sensor_id": "401560",
        "position": [
            37.357526,
            -121.907884
        ],
        "content": "401560 : 37.357526 , -121.907884"
    },
    {
        "sensor_id": "401567",
        "position": [
            37.279628,
            -121.864838
        ],
        "content": "401567 : 37.279628 , -121.864838"
    },
    {
        "sensor_id": "401597",
        "position": [
            37.2874,
            -121.869623
        ],
        "content": "401597 : 37.2874 , -121.869623"
    },
    {
        "sensor_id": "401606",
        "position": [
            37.287298,
            -121.869548
        ],
        "content": "401606 : 37.287298 , -121.869548"
    },
    {
        "sensor_id": "401611",
        "position": [
            37.318919,
            -121.940307
        ],
        "content": "401611 : 37.318919 , -121.940307"
    },
    {
        "sensor_id": "401655",
        "position": [
            37.335596,
            -121.858919
        ],
        "content": "401655 : 37.335596 , -121.858919"
    },
    {
        "sensor_id": "401808",
        "position": [
            37.334883,
            -121.860066
        ],
        "content": "401808 : 37.334883 , -121.860066"
    },
    {
        "sensor_id": "401809",
        "position": [
            37.334524,
            -121.860098
        ],
        "content": "401809 : 37.334524 , -121.860098"
    },
    {
        "sensor_id": "401810",
        "position": [
            37.32592,
            -121.883989
        ],
        "content": "401810 : 37.32592 , -121.883989"
    },
    {
        "sensor_id": "401811",
        "position": [
            37.325651,
            -121.883953
        ],
        "content": "401811 : 37.325651 , -121.883953"
    },
    {
        "sensor_id": "401816",
        "position": [
            37.37116,
            -121.926885
        ],
        "content": "401816 : 37.37116 , -121.926885"
    },
    {
        "sensor_id": "401817",
        "position": [
            37.371274,
            -121.926917
        ],
        "content": "401817 : 37.371274 , -121.926917"
    },
    {
        "sensor_id": "401845",
        "position": [
            37.332668,
            -122.060628
        ],
        "content": "401845 : 37.332668 , -122.060628"
    },
    {
        "sensor_id": "401846",
        "position": [
            37.332482,
            -122.060617
        ],
        "content": "401846 : 37.332482 , -122.060617"
    },
    {
        "sensor_id": "401890",
        "position": [
            37.343447,
            -121.855539
        ],
        "content": "401890 : 37.343447 , -121.855539"
    },
    {
        "sensor_id": "401891",
        "position": [
            37.343293,
            -121.855795
        ],
        "content": "401891 : 37.343293 , -121.855795"
    },
    {
        "sensor_id": "401906",
        "position": [
            37.335259,
            -121.848031
        ],
        "content": "401906 : 37.335259 , -121.848031"
    },
    {
        "sensor_id": "401908",
        "position": [
            37.335284,
            -121.847662
        ],
        "content": "401908 : 37.335284 , -121.847662"
    },
    {
        "sensor_id": "401926",
        "position": [
            37.411999,
            -122.078452
        ],
        "content": "401926 : 37.411999 , -122.078452"
    },
    {
        "sensor_id": "401936",
        "position": [
            37.407282,
            -122.06515
        ],
        "content": "401936 : 37.407282 , -122.06515"
    },
    {
        "sensor_id": "401937",
        "position": [
            37.411338,
            -122.076826
        ],
        "content": "401937 : 37.411338 , -122.076826"
    },
    {
        "sensor_id": "401942",
        "position": [
            37.322594,
            -121.897858
        ],
        "content": "401942 : 37.322594 , -121.897858"
    },
    {
        "sensor_id": "401943",
        "position": [
            37.322361,
            -121.8978
        ],
        "content": "401943 : 37.322361 , -121.8978"
    },
    {
        "sensor_id": "401948",
        "position": [
            37.409514,
            -122.071728
        ],
        "content": "401948 : 37.409514 , -122.071728"
    },
    {
        "sensor_id": "401957",
        "position": [
            37.270311,
            -121.861079
        ],
        "content": "401957 : 37.270311 , -121.861079"
    },
    {
        "sensor_id": "401958",
        "position": [
            37.270209,
            -121.860998
        ],
        "content": "401958 : 37.270209 , -121.860998"
    },
    {
        "sensor_id": "401994",
        "position": [
            37.385523,
            -121.975872
        ],
        "content": "401994 : 37.385523 , -121.975872"
    },
    {
        "sensor_id": "401996",
        "position": [
            37.396411,
            -122.015716
        ],
        "content": "401996 : 37.396411 , -122.015716"
    },
    {
        "sensor_id": "401997",
        "position": [
            37.398597,
            -122.025693
        ],
        "content": "401997 : 37.398597 , -122.025693"
    },
    {
        "sensor_id": "401998",
        "position": [
            37.404178,
            -122.05107
        ],
        "content": "401998 : 37.404178 , -122.05107"
    },
    {
        "sensor_id": "402056",
        "position": [
            37.328954,
            -121.895643
        ],
        "content": "402056 : 37.328954 , -121.895643"
    },
    {
        "sensor_id": "402057",
        "position": [
            37.336401,
            -121.897563
        ],
        "content": "402057 : 37.336401 , -121.897563"
    },
    {
        "sensor_id": "402058",
        "position": [
            37.337137,
            -121.897741
        ],
        "content": "402058 : 37.337137 , -121.897741"
    },
    {
        "sensor_id": "402059",
        "position": [
            37.337479,
            -121.897848
        ],
        "content": "402059 : 37.337479 , -121.897848"
    },
    {
        "sensor_id": "402060",
        "position": [
            37.356655,
            -122.062397
        ],
        "content": "402060 : 37.356655 , -122.062397"
    },
    {
        "sensor_id": "402061",
        "position": [
            37.356616,
            -122.06262
        ],
        "content": "402061 : 37.356616 , -122.06262"
    },
    {
        "sensor_id": "402067",
        "position": [
            37.321367,
            -121.899571
        ],
        "content": "402067 : 37.321367 , -121.899571"
    },
    {
        "sensor_id": "402117",
        "position": [
            37.344302,
            -121.902123
        ],
        "content": "402117 : 37.344302 , -121.902123"
    },
    {
        "sensor_id": "402118",
        "position": [
            37.344411,
            -121.902181
        ],
        "content": "402118 : 37.344411 , -121.902181"
    },
    {
        "sensor_id": "402119",
        "position": [
            37.421182,
            -121.915036
        ],
        "content": "402119 : 37.421182 , -121.915036"
    },
    {
        "sensor_id": "402120",
        "position": [
            37.399227,
            -121.908515
        ],
        "content": "402120 : 37.399227 , -121.908515"
    },
    {
        "sensor_id": "402121",
        "position": [
            37.380274,
            -121.904061
        ],
        "content": "402121 : 37.380274 , -121.904061"
    },
    {
        "sensor_id": "402281",
        "position": [
            37.38449,
            -121.904845
        ],
        "content": "402281 : 37.38449 , -121.904845"
    },
    {
        "sensor_id": "402282",
        "position": [
            37.384485,
            -121.905044
        ],
        "content": "402282 : 37.384485 , -121.905044"
    },
    {
        "sensor_id": "402283",
        "position": [
            37.391595,
            -121.906506
        ],
        "content": "402283 : 37.391595 , -121.906506"
    },
    {
        "sensor_id": "402284",
        "position": [
            37.391557,
            -121.90671
        ],
        "content": "402284 : 37.391557 , -121.90671"
    },
    {
        "sensor_id": "402285",
        "position": [
            37.398698,
            -121.908172
        ],
        "content": "402285 : 37.398698 , -121.908172"
    },
    {
        "sensor_id": "402286",
        "position": [
            37.405824,
            -121.909842
        ],
        "content": "402286 : 37.405824 , -121.909842"
    },
    {
        "sensor_id": "402287",
        "position": [
            37.405777,
            -121.910072
        ],
        "content": "402287 : 37.405777 , -121.910072"
    },
    {
        "sensor_id": "402288",
        "position": [
            37.419153,
            -121.914103
        ],
        "content": "402288 : 37.419153 , -121.914103"
    },
    {
        "sensor_id": "402289",
        "position": [
            37.419106,
            -121.914308
        ],
        "content": "402289 : 37.419106 , -121.914308"
    },
    {
        "sensor_id": "402359",
        "position": [
            37.329728,
            -121.842102
        ],
        "content": "402359 : 37.329728 , -121.842102"
    },
    {
        "sensor_id": "402360",
        "position": [
            37.329591,
            -121.842361
        ],
        "content": "402360 : 37.329591 , -121.842361"
    },
    {
        "sensor_id": "402361",
        "position": [
            37.336549,
            -121.848881
        ],
        "content": "402361 : 37.336549 , -121.848881"
    },
    {
        "sensor_id": "402362",
        "position": [
            37.358996,
            -121.871981
        ],
        "content": "402362 : 37.358996 , -121.871981"
    },
    {
        "sensor_id": "402363",
        "position": [
            37.3588,
            -121.872094
        ],
        "content": "402363 : 37.3588 , -121.872094"
    },
    {
        "sensor_id": "402364",
        "position": [
            37.368104,
            -121.90788
        ],
        "content": "402364 : 37.368104 , -121.90788"
    },
    {
        "sensor_id": "402365",
        "position": [
            37.367859,
            -121.907971
        ],
        "content": "402365 : 37.367859 , -121.907971"
    },
    {
        "sensor_id": "402366",
        "position": [
            37.388542,
            -121.986478
        ],
        "content": "402366 : 37.388542 , -121.986478"
    },
    {
        "sensor_id": "402367",
        "position": [
            37.388372,
            -121.986538
        ],
        "content": "402367 : 37.388372 , -121.986538"
    },
    {
        "sensor_id": "402368",
        "position": [
            37.393954,
            -122.005269
        ],
        "content": "402368 : 37.393954 , -122.005269"
    },
    {
        "sensor_id": "402369",
        "position": [
            37.393755,
            -122.005329
        ],
        "content": "402369 : 37.393755 , -122.005329"
    },
    {
        "sensor_id": "402370",
        "position": [
            37.39592,
            -122.013438
        ],
        "content": "402370 : 37.39592 , -122.013438"
    },
    {
        "sensor_id": "402371",
        "position": [
            37.396611,
            -122.017518
        ],
        "content": "402371 : 37.396611 , -122.017518"
    },
    {
        "sensor_id": "402372",
        "position": [
            37.40547,
            -122.055924
        ],
        "content": "402372 : 37.40547 , -122.055924"
    },
    {
        "sensor_id": "402373",
        "position": [
            37.405335,
            -122.056343
        ],
        "content": "402373 : 37.405335 , -122.056343"
    },
    {
        "sensor_id": "403225",
        "position": [
            37.349517,
            -121.91728
        ],
        "content": "403225 : 37.349517 , -121.91728"
    },
    {
        "sensor_id": "403265",
        "position": [
            37.349229,
            -121.917686
        ],
        "content": "403265 : 37.349229 , -121.917686"
    },
    {
        "sensor_id": "403329",
        "position": [
            37.270267,
            -121.947353
        ],
        "content": "403329 : 37.270267 , -121.947353"
    },
    {
        "sensor_id": "403401",
        "position": [
            37.328484,
            -121.870843
        ],
        "content": "403401 : 37.328484 , -121.870843"
    },
    {
        "sensor_id": "403402",
        "position": [
            37.32872,
            -121.870796
        ],
        "content": "403402 : 37.32872 , -121.870796"
    },
    {
        "sensor_id": "403404",
        "position": [
            37.327807,
            -121.874899
        ],
        "content": "403404 : 37.327807 , -121.874899"
    },
    {
        "sensor_id": "403406",
        "position": [
            37.32592,
            -121.883314
        ],
        "content": "403406 : 37.32592 , -121.883314"
    },
    {
        "sensor_id": "403409",
        "position": [
            37.324015,
            -121.890673
        ],
        "content": "403409 : 37.324015 , -121.890673"
    },
    {
        "sensor_id": "403412",
        "position": [
            37.32243,
            -121.89764
        ],
        "content": "403412 : 37.32243 , -121.89764"
    },
    {
        "sensor_id": "403414",
        "position": [
            37.314844,
            -121.913648
        ],
        "content": "403414 : 37.314844 , -121.913648"
    },
    {
        "sensor_id": "403419",
        "position": [
            37.316766,
            -121.921548
        ],
        "content": "403419 : 37.316766 , -121.921548"
    },
    {
        "sensor_id": "404370",
        "position": [
            37.296028,
            -121.939132
        ],
        "content": "404370 : 37.296028 , -121.939132"
    },
    {
        "sensor_id": "404434",
        "position": [
            37.265521,
            -121.98154
        ],
        "content": "404434 : 37.265521 , -121.98154"
    },
    {
        "sensor_id": "404435",
        "position": [
            37.326592,
            -122.050852
        ],
        "content": "404435 : 37.326592 , -122.050852"
    },
    {
        "sensor_id": "404444",
        "position": [
            37.265311,
            -121.981694
        ],
        "content": "404444 : 37.265311 , -121.981694"
    },
    {
        "sensor_id": "404451",
        "position": [
            37.27263,
            -121.862544
        ],
        "content": "404451 : 37.27263 , -121.862544"
    },
    {
        "sensor_id": "404452",
        "position": [
            37.284773,
            -121.867709
        ],
        "content": "404452 : 37.284773 , -121.867709"
    },
    {
        "sensor_id": "404453",
        "position": [
            37.309111,
            -121.882596
        ],
        "content": "404453 : 37.309111 , -121.882596"
    },
    {
        "sensor_id": "404461",
        "position": [
            37.309012,
            -121.882518
        ],
        "content": "404461 : 37.309012 , -121.882518"
    },
    {
        "sensor_id": "404462",
        "position": [
            37.272658,
            -121.862556
        ],
        "content": "404462 : 37.272658 , -121.862556"
    },
    {
        "sensor_id": "404521",
        "position": [
            37.382586,
            -121.965617
        ],
        "content": "404521 : 37.382586 , -121.965617"
    },
    {
        "sensor_id": "404522",
        "position": [
            37.402071,
            -122.041627
        ],
        "content": "404522 : 37.402071 , -122.041627"
    },
    {
        "sensor_id": "404553",
        "position": [
            37.395734,
            -122.013489
        ],
        "content": "404553 : 37.395734 , -122.013489"
    },
    {
        "sensor_id": "404554",
        "position": [
            37.401893,
            -122.041683
        ],
        "content": "404554 : 37.401893 , -122.041683"
    },
    {
        "sensor_id": "404585",
        "position": [
            37.406298,
            -122.011605
        ],
        "content": "404585 : 37.406298 , -122.011605"
    },
    {
        "sensor_id": "404586",
        "position": [
            37.406475,
            -122.011621
        ],
        "content": "404586 : 37.406475 , -122.011621"
    },
    {
        "sensor_id": "404640",
        "position": [
            37.333614,
            -122.049627
        ],
        "content": "404640 : 37.333614 , -122.049627"
    },
    {
        "sensor_id": "404753",
        "position": [
            37.364689,
            -121.902989
        ],
        "content": "404753 : 37.364689 , -121.902989"
    },
    {
        "sensor_id": "404759",
        "position": [
            37.365167,
            -121.901551
        ],
        "content": "404759 : 37.365167 , -121.901551"
    },
    {
        "sensor_id": "405613",
        "position": [
            37.262704,
            -121.858533
        ],
        "content": "405613 : 37.262704 , -121.858533"
    },
    {
        "sensor_id": "405619",
        "position": [
            37.284665,
            -121.867631
        ],
        "content": "405619 : 37.284665 , -121.867631"
    },
    {
        "sensor_id": "405701",
        "position": [
            37.316969,
            -121.924481
        ],
        "content": "405701 : 37.316969 , -121.924481"
    },
    {
        "sensor_id": "407150",
        "position": [
            37.427274,
            -121.884436
        ],
        "content": "407150 : 37.427274 , -121.884436"
    },
    {
        "sensor_id": "407151",
        "position": [
            37.420741,
            -121.882093
        ],
        "content": "407151 : 37.420741 , -121.882093"
    },
    {
        "sensor_id": "407152",
        "position": [
            37.416073,
            -121.880751
        ],
        "content": "407152 : 37.416073 , -121.880751"
    },
    {
        "sensor_id": "407153",
        "position": [
            37.398059,
            -121.875211
        ],
        "content": "407153 : 37.398059 , -121.875211"
    },
    {
        "sensor_id": "407155",
        "position": [
            37.391513,
            -121.870376
        ],
        "content": "407155 : 37.391513 , -121.870376"
    },
    {
        "sensor_id": "407157",
        "position": [
            37.385475,
            -121.863839
        ],
        "content": "407157 : 37.385475 , -121.863839"
    },
    {
        "sensor_id": "407161",
        "position": [
            37.40777,
            -121.878234
        ],
        "content": "407161 : 37.40777 , -121.878234"
    },
    {
        "sensor_id": "407165",
        "position": [
            37.344023,
            -121.845368
        ],
        "content": "407165 : 37.344023 , -121.845368"
    },
    {
        "sensor_id": "407172",
        "position": [
            37.341738,
            -121.848369
        ],
        "content": "407172 : 37.341738 , -121.848369"
    },
    {
        "sensor_id": "407173",
        "position": [
            37.342007,
            -121.847982
        ],
        "content": "407173 : 37.342007 , -121.847982"
    },
    {
        "sensor_id": "407174",
        "position": [
            37.40088,
            -121.876103
        ],
        "content": "407174 : 37.40088 , -121.876103"
    },
    {
        "sensor_id": "407176",
        "position": [
            37.358523,
            -121.840267
        ],
        "content": "407176 : 37.358523 , -121.840267"
    },
    {
        "sensor_id": "407177",
        "position": [
            37.360223,
            -121.841285
        ],
        "content": "407177 : 37.360223 , -121.841285"
    },
    {
        "sensor_id": "407179",
        "position": [
            37.368611,
            -121.846609
        ],
        "content": "407179 : 37.368611 , -121.846609"
    },
    {
        "sensor_id": "407180",
        "position": [
            37.372785,
            -121.850839
        ],
        "content": "407180 : 37.372785 , -121.850839"
    },
    {
        "sensor_id": "407181",
        "position": [
            37.379684,
            -121.857783
        ],
        "content": "407181 : 37.379684 , -121.857783"
    },
    {
        "sensor_id": "407184",
        "position": [
            37.427403,
            -121.884848
        ],
        "content": "407184 : 37.427403 , -121.884848"
    },
    {
        "sensor_id": "407185",
        "position": [
            37.420881,
            -121.882423
        ],
        "content": "407185 : 37.420881 , -121.882423"
    },
    {
        "sensor_id": "407186",
        "position": [
            37.391614,
            -121.870798
        ],
        "content": "407186 : 37.391614 , -121.870798"
    },
    {
        "sensor_id": "407187",
        "position": [
            37.383139,
            -121.861675
        ],
        "content": "407187 : 37.383139 , -121.861675"
    },
    {
        "sensor_id": "407190",
        "position": [
            37.412704,
            -121.880023
        ],
        "content": "407190 : 37.412704 , -121.880023"
    },
    {
        "sensor_id": "407191",
        "position": [
            37.407919,
            -121.878542
        ],
        "content": "407191 : 37.407919 , -121.878542"
    },
    {
        "sensor_id": "407194",
        "position": [
            37.344191,
            -121.845564
        ],
        "content": "407194 : 37.344191 , -121.845564"
    },
    {
        "sensor_id": "407200",
        "position": [
            37.398207,
            -121.875543
        ],
        "content": "407200 : 37.398207 , -121.875543"
    },
    {
        "sensor_id": "407202",
        "position": [
            37.360613,
            -121.841794
        ],
        "content": "407202 : 37.360613 , -121.841794"
    },
    {
        "sensor_id": "407204",
        "position": [
            37.366097,
            -121.845103
        ],
        "content": "407204 : 37.366097 , -121.845103"
    },
    {
        "sensor_id": "407206",
        "position": [
            37.372897,
            -121.851246
        ],
        "content": "407206 : 37.372897 , -121.851246"
    },
    {
        "sensor_id": "407207",
        "position": [
            37.379794,
            -121.858188
        ],
        "content": "407207 : 37.379794 , -121.858188"
    },
    {
        "sensor_id": "407321",
        "position": [
            37.333648,
            -122.056851
        ],
        "content": "407321 : 37.333648 , -122.056851"
    },
    {
        "sensor_id": "407323",
        "position": [
            37.396419,
            -122.068661
        ],
        "content": "407323 : 37.396419 , -122.068661"
    },
    {
        "sensor_id": "407325",
        "position": [
            37.383707,
            -122.068108
        ],
        "content": "407325 : 37.383707 , -122.068108"
    },
    {
        "sensor_id": "407328",
        "position": [
            37.377217,
            -122.067542
        ],
        "content": "407328 : 37.377217 , -122.067542"
    },
    {
        "sensor_id": "407331",
        "position": [
            37.335431,
            -122.058337
        ],
        "content": "407331 : 37.335431 , -122.058337"
    },
    {
        "sensor_id": "407332",
        "position": [
            37.407311,
            -122.069566
        ],
        "content": "407332 : 37.407311 , -122.069566"
    },
    {
        "sensor_id": "407335",
        "position": [
            37.373213,
            -122.067368
        ],
        "content": "407335 : 37.373213 , -122.067368"
    },
    {
        "sensor_id": "407336",
        "position": [
            37.363146,
            -122.062707
        ],
        "content": "407336 : 37.363146 , -122.062707"
    },
    {
        "sensor_id": "407337",
        "position": [
            37.353092,
            -122.0609
        ],
        "content": "407337 : 37.353092 , -122.0609"
    },
    {
        "sensor_id": "407339",
        "position": [
            37.351571,
            -122.060285
        ],
        "content": "407339 : 37.351571 , -122.060285"
    },
    {
        "sensor_id": "407341",
        "position": [
            37.344713,
            -122.059766
        ],
        "content": "407341 : 37.344713 , -122.059766"
    },
    {
        "sensor_id": "407342",
        "position": [
            37.379094,
            -122.067604
        ],
        "content": "407342 : 37.379094 , -122.067604"
    },
    {
        "sensor_id": "407344",
        "position": [
            37.331501,
            -122.054687
        ],
        "content": "407344 : 37.331501 , -122.054687"
    },
    {
        "sensor_id": "407348",
        "position": [
            37.384273,
            -122.068412
        ],
        "content": "407348 : 37.384273 , -122.068412"
    },
    {
        "sensor_id": "407352",
        "position": [
            37.377057,
            -122.067805
        ],
        "content": "407352 : 37.377057 , -122.067805"
    },
    {
        "sensor_id": "407359",
        "position": [
            37.407147,
            -122.070055
        ],
        "content": "407359 : 37.407147 , -122.070055"
    },
    {
        "sensor_id": "407360",
        "position": [
            37.373187,
            -122.067646
        ],
        "content": "407360 : 37.373187 , -122.067646"
    },
    {
        "sensor_id": "407361",
        "position": [
            37.363107,
            -122.063006
        ],
        "content": "407361 : 37.363107 , -122.063006"
    },
    {
        "sensor_id": "407364",
        "position": [
            37.351529,
            -122.060518
        ],
        "content": "407364 : 37.351529 , -122.060518"
    },
    {
        "sensor_id": "407367",
        "position": [
            37.379368,
            -122.067871
        ],
        "content": "407367 : 37.379368 , -122.067871"
    },
    {
        "sensor_id": "407370",
        "position": [
            37.333574,
            -122.057007
        ],
        "content": "407370 : 37.333574 , -122.057007"
    },
    {
        "sensor_id": "407372",
        "position": [
            37.344708,
            -122.059991
        ],
        "content": "407372 : 37.344708 , -122.059991"
    },
    {
        "sensor_id": "407373",
        "position": [
            37.337629,
            -122.059717
        ],
        "content": "407373 : 37.337629 , -122.059717"
    },
    {
        "sensor_id": "407374",
        "position": [
            37.395123,
            -122.068612
        ],
        "content": "407374 : 37.395123 , -122.068612"
    },
    {
        "sensor_id": "407710",
        "position": [
            37.317459,
            -121.938793
        ],
        "content": "407710 : 37.317459 , -121.938793"
    },
    {
        "sensor_id": "407711",
        "position": [
            37.317112,
            -121.941507
        ],
        "content": "407711 : 37.317112 , -121.941507"
    },
    {
        "sensor_id": "408907",
        "position": [
            37.321822,
            -121.940425
        ],
        "content": "408907 : 37.321822 , -121.940425"
    },
    {
        "sensor_id": "408911",
        "position": [
            37.325153,
            -121.940859
        ],
        "content": "408911 : 37.325153 , -121.940859"
    },
    {
        "sensor_id": "409524",
        "position": [
            37.348448,
            -121.907247
        ],
        "content": "409524 : 37.348448 , -121.907247"
    },
    {
        "sensor_id": "409525",
        "position": [
            37.362566,
            -121.917493
        ],
        "content": "409525 : 37.362566 , -121.917493"
    },
    {
        "sensor_id": "409526",
        "position": [
            37.366737,
            -121.921627
        ],
        "content": "409526 : 37.366737 , -121.921627"
    },
    {
        "sensor_id": "409528",
        "position": [
            37.362467,
            -121.917418
        ],
        "content": "409528 : 37.362467 , -121.917418"
    },
    {
        "sensor_id": "409529",
        "position": [
            37.366662,
            -121.921519
        ],
        "content": "409529 : 37.366662 , -121.921519"
    },
    {
        "sensor_id": "413026",
        "position": [
            37.421232,
            -121.914808
        ],
        "content": "413026 : 37.421232 , -121.914808"
    },
    {
        "sensor_id": "413845",
        "position": [
            37.422887,
            -121.925747
        ],
        "content": "413845 : 37.422887 , -121.925747"
    },
    {
        "sensor_id": "413877",
        "position": [
            37.321613,
            -121.899642
        ],
        "content": "413877 : 37.321613 , -121.899642"
    },
    {
        "sensor_id": "413878",
        "position": [
            37.324641,
            -121.888603
        ],
        "content": "413878 : 37.324641 , -121.888603"
    },
    {
        "sensor_id": "414284",
        "position": [
            37.323066,
            -121.896538
        ],
        "content": "414284 : 37.323066 , -121.896538"
    },
    {
        "sensor_id": "414694",
        "position": [
            37.315051,
            -121.913497
        ],
        "content": "414694 : 37.315051 , -121.913497"
    }
]